Metadata-Version: 1.0
Name: celebrity-births-AN-CW-IR
Version: 0.0.1
Summary: The best package that allows you to find celebrity by date of birth
Home-page: https://github.com/AdaobiNwafor/Celebrities-Births.git
Author: Adaobi Carys Imran
Author-email: UNKNOWN
License: MIT
Platform: UNKNOWN
